setup.py
PornHubV8/__init__.py
pornhub_downloader.egg-info/PKG-INFO
pornhub_downloader.egg-info/SOURCES.txt
pornhub_downloader.egg-info/dependency_links.txt
pornhub_downloader.egg-info/top_level.txt