Metadata-Version: 2.1
Name: pornhub-downloader
Version: 1
Summary: This Package For Download Videoas From PornHub and Xnxx
Author: m3ghos
Classifier: Programming Language :: Python :: 3
Classifier: Operating System :: OS Independent
Classifier: License :: OSI Approved :: MIT License
